[
    {
        "account_number": "15424850",
        "iban": "SM27U801800107076875605W8X4",
        "currency_code": "EUR",
        "balance": "514.77",
        "id": "1d6a98c76e98e13b73f50acf",
        "transactions": [
            {
                "createdAt": "2026-03-25T21:39:48.567Z",
                "transaction_type": "invoice",
                "transaction_description": "withdrawal processed at McGlynn Inc for BWP 871.92, using card ending ****5706. Account: ***6954.",
                "transactin_amount": "685.35",
                "id": "cfddaddff172e4982bd6dbcb"
            },
            {
                "createdAt": "2026-03-25T20:00:41.464Z",
                "transaction_type": "withdrawal",
                "transaction_description": "withdrawal transaction at McDermott Group using card ending with ****4892 for RSD 764.59 in account ***9290.",
                "transactin_amount": "255.92",
                "id": "e61a45dae4dd6fddefdaf2c8"
            },
            {
                "createdAt": "2026-03-25T22:15:53.925Z",
                "transaction_type": "deposit",
                "transaction_description": "payment of MAD 3.39 at Tillman Inc charged to account ending in 3147 using card ending in ****0521.",
                "transactin_amount": "800.84",
                "id": "e75c1ae7fcf1dbf9f35c4ed3"
            }
        ],
        "person_id": "cdb681c0f62daecdfdd8be1e"
    },
    {
        "account_number": "20698664",
        "iban": "SM97X7414413409821T574ZB078",
        "currency_code": "GYD",
        "balance": "428.72",
        "id": "6ef9abfc7edfeeecda2aec3e",
        "transactions": [
            {
                "createdAt": "2026-03-26T02:18:04.039Z",
                "transaction_type": "invoice",
                "transaction_description": "invoice processed at Schaden, Zemlak and Kuhic for HKD 525.45, using card ending ****5733. Account: ***7170.",
                "transactin_amount": "311.89",
                "id": "b94ce7739befd43e3db8bbc4"
            },
            {
                "createdAt": "2026-03-25T16:26:11.277Z",
                "transaction_type": "payment",
                "transaction_description": "invoice of CLP 814.64 at Kessler, Champlin and Strosin charged to account ending in 7256 using card ending in ****0786.",
                "transactin_amount": "522.26",
                "id": "d8821d0bebec61ed4b797615"
            },
            {
                "createdAt": "2026-03-25T16:50:16.126Z",
                "transaction_type": "deposit",
                "transaction_description": "A payment for OMR 430.85 was made at Raynor and Sons via card ending ****2929 on account ***8831.",
                "transactin_amount": "58.84",
                "id": "58168f48ffe37200babbdedc"
            }
        ],
        "person_id": "e4efba5446a010b595b6c5ee"
    },
    {
        "account_number": "78870357",
        "iban": "LI2375751M9Z5712G452N",
        "currency_code": "VND",
        "balance": "313.66",
        "id": "1c02dfaddcd8eaedea38139c",
        "transactions": [
            {
                "createdAt": "2026-03-26T07:13:53.558Z",
                "transaction_type": "withdrawal",
                "transaction_description": "Payment of ERN 739.68 for invoice at Schuster Inc, processed with card ending ****2492 linked to account ***3794.",
                "transactin_amount": "270.13",
                "id": "d33decbcf8ce09b1699baa45"
            },
            {
                "createdAt": "2026-03-25T23:18:34.577Z",
                "transaction_type": "withdrawal",
                "transaction_description": "deposit confirmed at Jaskolski Group for SOS 457.03, card ending in ****7413 associated with account ***5073.",
                "transactin_amount": "439.04",
                "id": "d6b51f68ae2df11ffdacdd3f"
            },
            {
                "createdAt": "2026-03-26T09:40:51.766Z",
                "transaction_type": "withdrawal",
                "transaction_description": "You made a deposit of ANG 256.28 at Franecki Inc using card ending in ****9216 from account ***9422.",
                "transactin_amount": "683.92",
                "id": "b1a7d1d2c35ba0bb57218e3d"
            }
        ],
        "person_id": "31a32a5e0db01319ad2d75e1"
    },
    {
        "account_number": "78250269",
        "iban": "DE79794870196992256021",
        "currency_code": "XPF",
        "balance": "207.38",
        "id": "0302177ba6fdbe4c6adb845f",
        "transactions": [
            {
                "createdAt": "2026-03-25T16:17:08.195Z",
                "transaction_type": "invoice",
                "transaction_description": "Transaction alert: withdrawal at Willms Group using card ending ****8305 for an amount of KGS 339.01 on account ***4384.",
                "transactin_amount": "792.45",
                "id": "2c5357963acefbaebd6eddfa"
            },
            {
                "createdAt": "2026-03-25T23:28:01.493Z",
                "transaction_type": "invoice",
                "transaction_description": "invoice transaction at Romaguera, Little and Johnson using card ending with ****2311 for XOF 706.79 in account ***6432.",
                "transactin_amount": "264.11",
                "id": "27cddb6b8de0ad6e9ed7b3ab"
            },
            {
                "createdAt": "2026-03-26T03:28:55.608Z",
                "transaction_type": "payment",
                "transaction_description": "payment confirmed at Pouros and Sons for MGA 565.78, card ending in ****6166 associated with account ***4718.",
                "transactin_amount": "201.56",
                "id": "56ecdb146a75fb03fbb8c7e7"
            }
        ],
        "person_id": "75ea4616c36ad4f95e3decca"
    },
    {
        "account_number": "91764733",
        "iban": "SM49W8970007532859104G1208Z",
        "currency_code": "BZD",
        "balance": "7.36",
        "id": "bfde7b5dcb264cbfd9dd4653",
        "transactions": [
            {
                "createdAt": "2026-03-26T07:30:20.132Z",
                "transaction_type": "payment",
                "transaction_description": "Transaction alert: payment at Roberts - Ebert using card ending ****6792 for an amount of DKK 890.68 on account ***4344.",
                "transactin_amount": "878.10",
                "id": "9fa0e17dcdae32bec5d1a7aa"
            },
            {
                "createdAt": "2026-03-25T18:33:26.553Z",
                "transaction_type": "deposit",
                "transaction_description": "You made a deposit of IRR 830.82 at Schmeler, Hane and West using card ending in ****2546 from account ***4753.",
                "transactin_amount": "957.68",
                "id": "8a04ef8bf6f14bcc88bababa"
            },
            {
                "createdAt": "2026-03-26T08:31:55.386Z",
                "transaction_type": "payment",
                "transaction_description": "payment processed at Wiza - Abshire for LRD 212.23, using card ending ****6237. Account: ***0967.",
                "transactin_amount": "446.90",
                "id": "dbf312cca3d3fad3814aea0f"
            }
        ],
        "person_id": "aa505ec2735fb51aa17d27f4"
    },
    {
        "account_number": "42876797",
        "iban": "SA521918411135D12947R75I",
        "currency_code": "MVR",
        "balance": "458.06",
        "id": "c5db25fecdedf2c50ee12e64",
        "transactions": [
            {
                "createdAt": "2026-03-25T16:26:25.324Z",
                "transaction_type": "withdrawal",
                "transaction_description": "Transaction alert: invoice at Kuphal - Corkery using card ending ****5373 for an amount of HNL 999.79 on account ***2430.",
                "transactin_amount": "394.99",
                "id": "7ad2f7da23d1811fd63a47a5"
            },
            {
                "createdAt": "2026-03-25T15:45:01.642Z",
                "transaction_type": "withdrawal",
                "transaction_description": "Transaction alert: withdrawal at Botsford Inc using card ending ****7422 for an amount of HTG 950.74 on account ***0728.",
                "transactin_amount": "621.52",
                "id": "c649adbfd7e8eda6fcb5dd8a"
            },
            {
                "createdAt": "2026-03-26T02:43:10.823Z",
                "transaction_type": "deposit",
                "transaction_description": "Payment of PGK 780.72 for invoice at Carter - Runolfsson, processed with card ending ****8436 linked to account ***5183.",
                "transactin_amount": "841.97",
                "id": "2a0adb716dbe93b8c9254fa6"
            }
        ],
        "person_id": "e4daaf4a9eb2f1422eda1aba"
    },
    {
        "account_number": "15870759",
        "iban": "GI77NPGZ812255566501EY8",
        "currency_code": "SYP",
        "balance": "188.46",
        "id": "4befdc7fa6eba8ebef0dfabe",
        "transactions": [
            {
                "createdAt": "2026-03-26T00:24:59.962Z",
                "transaction_type": "deposit",
                "transaction_description": "deposit transaction at Zemlak - Gulgowski using card ending with ****4998 for NGN 961.31 in account ***5477.",
                "transactin_amount": "258.32",
                "id": "ba9ddad6bde9f1c7c52af60f"
            },
            {
                "createdAt": "2026-03-26T00:40:27.942Z",
                "transaction_type": "withdrawal",
                "transaction_description": "Your deposit of BTN 499.52 at Wilkinson, Waelchi and Stiedemann was successful. Charged via card ****9862 to account ***3220.",
                "transactin_amount": "955.64",
                "id": "45cff5ae5efc4e0caa479eff"
            },
            {
                "createdAt": "2026-03-26T08:16:18.063Z",
                "transaction_type": "withdrawal",
                "transaction_description": "payment of YER 231.12 at Pfannerstill, Larson and Corwin charged to account ending in 3664 using card ending in ****4914.",
                "transactin_amount": "361.57",
                "id": "fa0ae9cf336e93c2a791d9de"
            }
        ],
        "person_id": "c6f7fc915ccfb0f723bfd45e"
    },
    {
        "account_number": "81657716",
        "iban": "AD64529660933I2010P191K9",
        "currency_code": "ARS",
        "balance": "475.37",
        "id": "3fb9e6124ca57065feddd7a4",
        "transactions": [
            {
                "createdAt": "2026-03-25T12:32:17.654Z",
                "transaction_type": "invoice",
                "transaction_description": "deposit processed at Johns - Murray for AED 308.01, using card ending ****7867. Account: ***7829.",
                "transactin_amount": "632.43",
                "id": "fccf127626fefddea665f54c"
            },
            {
                "createdAt": "2026-03-26T05:50:58.924Z",
                "transaction_type": "withdrawal",
                "transaction_description": "Transaction alert: invoice at Bode and Sons using card ending ****7108 for an amount of DJF 675.19 on account ***2487.",
                "transactin_amount": "503.68",
                "id": "fb0f29549b899977d07e7cd9"
            }
        ],
        "person_id": "a67e8ea4ef4525b8c9c14f1e"
    },
    {
        "account_number": "94726295",
        "iban": "TR592044225505917002060012",
        "currency_code": "SEK",
        "balance": "726.18",
        "id": "1c432cead4ade8eb98ef2aec",
        "transactions": [
            {
                "createdAt": "2026-03-25T22:03:14.155Z",
                "transaction_type": "deposit",
                "transaction_description": "invoice confirmed at Moore - Welch for PEN 738.87, card ending in ****4070 associated with account ***5450.",
                "transactin_amount": "269.90",
                "id": "2dd5eea1d452cf8ceecbfe51"
            },
            {
                "createdAt": "2026-03-25T14:54:23.907Z",
                "transaction_type": "withdrawal",
                "transaction_description": "withdrawal of IQD 782.57 at Runte, West and Berge charged to account ending in 0300 using card ending in ****9471.",
                "transactin_amount": "275.68",
                "id": "8534da367ececac4c64ece72"
            }
        ],
        "person_id": "ac217bea6cbf219d25f3b9b4"
    },
    {
        "account_number": "99408887",
        "iban": "IE23258624396239040002",
        "currency_code": "OMR",
        "balance": "961.29",
        "id": "ececa040afdedbf0b0f778cc",
        "transactions": [
            {
                "createdAt": "2026-03-25T17:24:15.376Z",
                "transaction_type": "withdrawal",
                "transaction_description": "A withdrawal of LSL 636.29 occurred at Koss Inc using a card ending in ****2334 for account ***2401.",
                "transactin_amount": "580.35",
                "id": "fdca3a3e2730dbc7c067a3de"
            },
            {
                "createdAt": "2026-03-25T17:23:50.068Z",
                "transaction_type": "deposit",
                "transaction_description": "invoice transaction at Nicolas - Price using card ending with ****7940 for BIF 861.52 in account ***7885.",
                "transactin_amount": "958.00",
                "id": "c9c73beadb1c27fbd24b3599"
            }
        ],
        "person_id": "f9817de6124ae4fa4d8b766a"
    },
    {
        "account_number": "25518146",
        "iban": "PK38AKKC7980010630101009",
        "currency_code": "BYN",
        "balance": "440.25",
        "id": "e2fa35a94dba40bbae62a5eb",
        "transactions": [
            {
                "createdAt": "2026-03-26T08:40:41.340Z",
                "transaction_type": "deposit",
                "transaction_description": "Payment of BDT 101.06 for payment at Connelly, Nitzsche and Zboncak, processed with card ending ****5059 linked to account ***8218.",
                "transactin_amount": "977.85",
                "id": "ecf5d4ec2cfcc7d8eaadbedf"
            },
            {
                "createdAt": "2026-03-26T07:08:49.382Z",
                "transaction_type": "withdrawal",
                "transaction_description": "A withdrawal of SCR 659.80 occurred at Wuckert LLC using a card ending in ****1299 for account ***6875.",
                "transactin_amount": "824.60",
                "id": "adc87ffcd8d0c65d23dcb2d8"
            }
        ],
        "person_id": "f01cb12bae4ccdd5a8ea7a8c"
    },
    {
        "account_number": "46442648",
        "iban": "NL53YHRO0955803001",
        "currency_code": "IRR",
        "balance": "620.14",
        "id": "3cb4e171423efa3f8ee19afc",
        "transactions": [
            {
                "createdAt": "2026-03-26T07:03:13.076Z",
                "transaction_type": "deposit",
                "transaction_description": "invoice confirmed at Ward, Kemmer and Osinski for BTN 231.71, card ending in ****4502 associated with account ***0004.",
                "transactin_amount": "241.63",
                "id": "794e7dff230f7adb89b4ebd7"
            },
            {
                "createdAt": "2026-03-25T22:20:11.369Z",
                "transaction_type": "invoice",
                "transaction_description": "deposit of LKR 162.02 at Adams, Kshlerin and Swift charged to account ending in 9376 using card ending in ****3978.",
                "transactin_amount": "167.39",
                "id": "c4dc8b2bec0769cac0b1a9f8"
            }
        ],
        "person_id": "bf49a6e64ead9430d8041aca"
    },
    {
        "account_number": "32354082",
        "iban": "FR7084045300077BVO179051700",
        "currency_code": "PGK",
        "balance": "803.44",
        "id": "e41d7b4f334d60e69ef7cbb1",
        "transactions": [
            {
                "createdAt": "2026-03-26T00:09:37.415Z",
                "transaction_type": "deposit",
                "transaction_description": "Your payment of MDL 692.54 at Pagac, Orn and Keeling was successful. Charged via card ****5816 to account ***7630.",
                "transactin_amount": "396.63",
                "id": "f5ff5851a5ad6541aed18969"
            },
            {
                "createdAt": "2026-03-25T21:49:30.673Z",
                "transaction_type": "payment",
                "transaction_description": "Your payment of CZK 830.67 at Skiles LLC was successful. Charged via card ****3192 to account ***7235.",
                "transactin_amount": "232.57",
                "id": "1c4aacec03c03dacbdbedeef"
            }
        ],
        "person_id": "cfcbbdcbc21cbeaece1225df"
    },
    {
        "account_number": "38648570",
        "iban": "HU43442219030487503160010572",
        "currency_code": "LRD",
        "balance": "574.93",
        "id": "6265942f823ac09c83b02c1d",
        "transactions": [
            {
                "createdAt": "2026-03-25T15:31:04.785Z",
                "transaction_type": "invoice",
                "transaction_description": "withdrawal confirmed at VonRueden and Sons for NOK 272.28, card ending in ****4888 associated with account ***3551.",
                "transactin_amount": "887.21",
                "id": "1f32fcde1baa09dce3bf2dff"
            },
            {
                "createdAt": "2026-03-26T07:45:58.247Z",
                "transaction_type": "withdrawal",
                "transaction_description": "Transaction alert: withdrawal at Koelpin Group using card ending ****5877 for an amount of FKP 806.72 on account ***8903.",
                "transactin_amount": "550.93",
                "id": "aa717428bb6dc51d2e9dabb0"
            }
        ],
        "person_id": "3dceeca1f578bcd116026ee9"
    },
    {
        "account_number": "43292631",
        "iban": "DE79783013661300353844",
        "currency_code": "CVE",
        "balance": "62.82",
        "id": "beecadecfc8ad5de41eff8aa",
        "transactions": [
            {
                "createdAt": "2026-03-26T11:11:10.851Z",
                "transaction_type": "invoice",
                "transaction_description": "A payment for CUP 469.13 was made at Daugherty - Turner via card ending ****9264 on account ***4047.",
                "transactin_amount": "262.31",
                "id": "0deafa85edeae98ef6aefed3"
            },
            {
                "createdAt": "2026-03-26T09:42:56.972Z",
                "transaction_type": "invoice",
                "transaction_description": "Your invoice of PAB 109.27 at Moen - Renner was successful. Charged via card ****0315 to account ***1579.",
                "transactin_amount": "364.30",
                "id": "cef3a209cf7ccf1b1e50f0b9"
            }
        ],
        "person_id": "a71e2edebceceadfabf7fcf9"
    },
    {
        "account_number": "15771222",
        "iban": "GI91MKBU90339I1129885U1",
        "currency_code": "RSD",
        "balance": "323.93",
        "id": "3f73adbddfc93e5bbf57d198",
        "transactions": [
            {
                "createdAt": "2026-03-25T14:22:34.076Z",
                "transaction_type": "withdrawal",
                "transaction_description": "Transaction alert: invoice at Kuphal - Beier using card ending ****5218 for an amount of RON 869.85 on account ***6701.",
                "transactin_amount": "289.13",
                "id": "eb08faddc7ff8434f5aa817d"
            },
            {
                "createdAt": "2026-03-26T05:29:33.190Z",
                "transaction_type": "deposit",
                "transaction_description": "Payment of ILS 562.58 for payment at Metz, Jast and Schroeder, processed with card ending ****4915 linked to account ***4010.",
                "transactin_amount": "356.80",
                "id": "b0eb02446e5bed69c9c8e7c0"
            }
        ],
        "person_id": "f0528163fcbabe235fcff07c"
    },
    {
        "account_number": "77427787",
        "iban": "MR5660050054413779085057225",
        "currency_code": "BMD",
        "balance": "963.72",
        "id": "cab5b773ecddb74d7abed642",
        "transactions": [
            {
                "createdAt": "2026-03-25T15:27:41.555Z",
                "transaction_type": "deposit",
                "transaction_description": "Transaction alert: invoice at Upton, Wisoky and Block using card ending ****4551 for an amount of DKK 272.59 on account ***1759.",
                "transactin_amount": "338.93",
                "id": "3382ccdeeffba7ee9dcbebd6"
            },
            {
                "createdAt": "2026-03-26T07:04:04.983Z",
                "transaction_type": "deposit",
                "transaction_description": "invoice transaction at Pacocha Inc using card ending with ****7119 for GEL 899.44 in account ***8959.",
                "transactin_amount": "37.16",
                "id": "cbe9eeee87eafc16d997841d"
            }
        ],
        "person_id": "cfb1ee1f38fa60daddd2b185"
    },
    {
        "account_number": "49263404",
        "iban": "AE097237044691325004685",
        "currency_code": "XCD",
        "balance": "910.64",
        "id": "b80a9851a2fa3258fddc1752",
        "transactions": [
            {
                "createdAt": "2026-03-26T06:24:14.850Z",
                "transaction_type": "invoice",
                "transaction_description": "invoice at Schimmel, Hagenes and Towne with a card ending in ****8807 for SCR 210.85 from account ***4057.",
                "transactin_amount": "107.91",
                "id": "88ea10b6b8cfc9deddbdd156"
            },
            {
                "createdAt": "2026-03-26T03:18:52.431Z",
                "transaction_type": "deposit",
                "transaction_description": "You made a payment of AUD 442.24 at Ankunding, Runte and Morar using card ending in ****6140 from account ***8793.",
                "transactin_amount": "385.07",
                "id": "ed4406daeda6b26d4fac448a"
            }
        ],
        "person_id": "0d0a2687d935d69e6bbec175"
    },
    {
        "account_number": "53880112",
        "iban": "GI51AIGP11O311629176028",
        "currency_code": "RON",
        "balance": "105.97",
        "id": "d0981dbbccb0addf26d00cd4",
        "transactions": [
            {
                "createdAt": "2026-03-26T11:13:57.626Z",
                "transaction_type": "deposit",
                "transaction_description": "Your withdrawal of MRU 319.45 at Mraz - McKenzie was successful. Charged via card ****7858 to account ***8824.",
                "transactin_amount": "780.72",
                "id": "78dfe120cb97aec1d5dd2dd2"
            },
            {
                "createdAt": "2026-03-25T18:58:22.315Z",
                "transaction_type": "deposit",
                "transaction_description": "payment transaction at Nicolas - Olson using card ending with ****2716 for SGD 93.59 in account ***9959.",
                "transactin_amount": "895.98",
                "id": "abf2efcea4eecefae2bc2a59"
            }
        ],
        "person_id": "3afacd3c8bd3fee2bcb83749"
    },
    {
        "account_number": "11991917",
        "iban": "KW92HAEGAU183715ZB904128488984",
        "currency_code": "MKD",
        "balance": "36.05",
        "id": "a19ee0faa40ac9df31338eb0",
        "transactions": [
            {
                "createdAt": "2026-03-26T03:39:05.699Z",
                "transaction_type": "payment",
                "transaction_description": "deposit transaction at Beahan and Sons using card ending with ****5842 for TRY 283.98 in account ***8070.",
                "transactin_amount": "658.07",
                "id": "8dffbbd49ac2fbbf6984eccb"
            },
            {
                "createdAt": "2026-03-26T05:04:22.398Z",
                "transaction_type": "invoice",
                "transaction_description": "A deposit for KPW 578.11 was made at Koch, Collier and Gutkowski via card ending ****4212 on account ***9197.",
                "transactin_amount": "585.69",
                "id": "84afe3d03a3deca20fe74ac4"
            }
        ],
        "person_id": "7cdacccbc05f5c78d74b1ebc"
    },
    {
        "account_number": "58400642",
        "iban": "DO61YRGT10056008467640741855",
        "currency_code": "FKP",
        "balance": "123.56",
        "id": "aeab1f8dcccb8b299d7fcddf",
        "transactions": [
            {
                "createdAt": "2026-03-25T12:52:42.259Z",
                "transaction_type": "deposit",
                "transaction_description": "Your invoice of SGD 234.09 at Herman, Jones and Kozey was successful. Charged via card ****8804 to account ***3228.",
                "transactin_amount": "814.33",
                "id": "dd962081dbfb5bcdc32a0ada"
            },
            {
                "createdAt": "2026-03-25T20:48:19.259Z",
                "transaction_type": "invoice",
                "transaction_description": "payment at Crona - Weissnat with a card ending in ****9050 for AOA 59.29 from account ***4737.",
                "transactin_amount": "166.08",
                "id": "d1130dffef4640b23e1cffca"
            }
        ],
        "person_id": "ed5bf5bfc58c5bae214efeaf"
    },
    {
        "account_number": "67835720",
        "iban": "FI5131043104090079",
        "currency_code": "MKD",
        "balance": "516.45",
        "id": "63f5a07b056d99f473c63a4a",
        "transactions": [
            {
                "createdAt": "2026-03-25T19:14:05.599Z",
                "transaction_type": "invoice",
                "transaction_description": "payment of XAF 152.71 at Farrell and Sons charged to account ending in 0146 using card ending in ****0235.",
                "transactin_amount": "447.52",
                "id": "ab1cac1a6dfe551d718bccb3"
            },
            {
                "createdAt": "2026-03-25T19:30:34.996Z",
                "transaction_type": "withdrawal",
                "transaction_description": "invoice at Schowalter Inc with a card ending in ****6892 for MDL 108.02 from account ***4681.",
                "transactin_amount": "206.80",
                "id": "803a0da01b71eab5fac2be8c"
            }
        ],
        "person_id": "10a1d8da44be1dc4bf426059"
    },
    {
        "account_number": "91645895",
        "iban": "AT169009359060100300",
        "currency_code": "TTD",
        "balance": "752.95",
        "id": "db5fa7d0fd80ab856dd41c4d",
        "transactions": [
            {
                "createdAt": "2026-03-25T19:49:04.851Z",
                "transaction_type": "invoice",
                "transaction_description": "invoice at Berge LLC with a card ending in ****0473 for TJS 144.45 from account ***0000.",
                "transactin_amount": "252.69",
                "id": "65c40d38f8aafe32f33bf65f"
            },
            {
                "createdAt": "2026-03-25T20:41:07.460Z",
                "transaction_type": "withdrawal",
                "transaction_description": "A deposit for XAF 174.19 was made at Mayer Group via card ending ****7258 on account ***9332.",
                "transactin_amount": "232.03",
                "id": "78965a7fec375c4dc1ba9a6f"
            }
        ],
        "person_id": "2fec07fc372c28029d94a3b0"
    },
    {
        "account_number": "65177615",
        "iban": "NL05KTDF3700702993",
        "currency_code": "BTN",
        "balance": "711.84",
        "id": "edec751d2c4e32b3b8fb9db0",
        "transactions": [
            {
                "createdAt": "2026-03-26T00:31:35.095Z",
                "transaction_type": "payment",
                "transaction_description": "Your payment of ETB 913.91 at Dooley - Erdman was successful. Charged via card ****8929 to account ***3984.",
                "transactin_amount": "263.22",
                "id": "3268d1f078d7c0693ee8441e"
            },
            {
                "createdAt": "2026-03-26T06:05:24.311Z",
                "transaction_type": "invoice",
                "transaction_description": "invoice at Stoltenberg - Rempel with a card ending in ****6916 for MVR 177.94 from account ***2046.",
                "transactin_amount": "997.07",
                "id": "8e6ad9bc0ddc5c4fab3f7e3b"
            }
        ],
        "person_id": "c5cdd16cdcaa8cbc66cbf1d8"
    },
    {
        "account_number": "04498562",
        "iban": "GB87QRRP18400870871185",
        "currency_code": "SDG",
        "balance": "272.55",
        "id": "bcf0ebbd6bce08e62bd13b5c",
        "transactions": [
            {
                "createdAt": "2026-03-25T22:20:20.147Z",
                "transaction_type": "invoice",
                "transaction_description": "Payment of JMD 161.27 for payment at Johnston Inc, processed with card ending ****7695 linked to account ***7223.",
                "transactin_amount": "495.41",
                "id": "3e32dbb6acb4abeb0f9772f0"
            },
            {
                "createdAt": "2026-03-25T13:50:06.468Z",
                "transaction_type": "invoice",
                "transaction_description": "withdrawal processed at Carter and Sons for CNY 273.76, using card ending ****1276. Account: ***8732.",
                "transactin_amount": "199.24",
                "id": "ffb076d019d4093331a75ca7"
            }
        ],
        "person_id": "df7a010f4fef6d11efcfd1e4"
    },
    {
        "account_number": "65252354",
        "iban": "FR300094984456Q756469633P81",
        "currency_code": "TWD",
        "balance": "48.88",
        "id": "ffb2ad38afa25e5ce19f2c26",
        "transactions": [
            {
                "createdAt": "2026-03-25T18:55:22.738Z",
                "transaction_type": "payment",
                "transaction_description": "invoice at Raynor, Daugherty and Howell with a card ending in ****8675 for TZS 227.41 from account ***6144.",
                "transactin_amount": "57.99",
                "id": "6cafb648ffc2bea6e5cb1033"
            },
            {
                "createdAt": "2026-03-25T21:28:03.371Z",
                "transaction_type": "payment",
                "transaction_description": "deposit confirmed at Hackett and Sons for HTG 420.27, card ending in ****8513 associated with account ***2086.",
                "transactin_amount": "849.64",
                "id": "51ff8b4f0a1ebd0b6fb60d41"
            }
        ],
        "person_id": "1dbd0daf4ff8bdd7a91e2de1"
    },
    {
        "account_number": "19004568",
        "iban": "LI40218438VX5R1303136",
        "currency_code": "UGX",
        "balance": "624.80",
        "id": "febbcc17292f53aa3b5aae5c",
        "transactions": [
            {
                "createdAt": "2026-03-25T14:15:04.979Z",
                "transaction_type": "deposit",
                "transaction_description": "Transaction alert: withdrawal at Erdman Inc using card ending ****6909 for an amount of XCD 644.91 on account ***6318.",
                "transactin_amount": "282.69",
                "id": "a7ceba01f5edd2ebdba09fe0"
            },
            {
                "createdAt": "2026-03-25T14:33:32.810Z",
                "transaction_type": "withdrawal",
                "transaction_description": "payment of GNF 876.92 at Lang, Nikolaus and Goldner charged to account ending in 4004 using card ending in ****9910.",
                "transactin_amount": "332.90",
                "id": "d07bb15ace9df8fef57fb4cc"
            }
        ],
        "person_id": "60dadfb0afa1b8e982b4dbb8"
    },
    {
        "account_number": "64090543",
        "iban": "LV30YXHF498A741738X18",
        "currency_code": "GTQ",
        "balance": "203.12",
        "id": "bf995d19de8e192addbe6c5d",
        "transactions": [
            {
                "createdAt": "2026-03-25T14:54:57.780Z",
                "transaction_type": "withdrawal",
                "transaction_description": "payment confirmed at Gutkowski Group for MKD 696.13, card ending in ****0297 associated with account ***2931.",
                "transactin_amount": "876.95",
                "id": "03a54001eaf33a9aca63adf9"
            },
            {
                "createdAt": "2026-03-26T01:17:45.343Z",
                "transaction_type": "deposit",
                "transaction_description": "A deposit for SZL 268.64 was made at Lakin LLC via card ending ****4327 on account ***3220.",
                "transactin_amount": "828.57",
                "id": "f82fbd5f1f49eee35bf3fba4"
            }
        ],
        "person_id": "d751c93cfb9f1a8a6f0eea7f"
    },
    {
        "account_number": "23759738",
        "iban": "MC8700604633507217N87944268",
        "currency_code": "ZWL",
        "balance": "628.55",
        "id": "fdd9fafe1bffbcda2fccffbb",
        "transactions": [
            {
                "createdAt": "2026-03-26T11:01:51.497Z",
                "transaction_type": "invoice",
                "transaction_description": "invoice processed at Bergnaum, Borer and Beatty for HTG 808.13, using card ending ****9106. Account: ***3988.",
                "transactin_amount": "941.59",
                "id": "3aca3a6057270e0dc5f46b05"
            },
            {
                "createdAt": "2026-03-25T12:22:12.149Z",
                "transaction_type": "withdrawal",
                "transaction_description": "A payment of MXN 475.89 occurred at Price, Morar and Shields using a card ending in ****7040 for account ***4486.",
                "transactin_amount": "746.45",
                "id": "86de365e340e1fbcdc3678ff"
            }
        ],
        "person_id": "7cacaafb0168e9b3ade55349"
    },
    {
        "account_number": "89401800",
        "iban": "IE853L7480201378798799",
        "currency_code": "PHP",
        "balance": "428.35",
        "id": "7d6f7ae8ea41eee35cdcde85",
        "transactions": [
            {
                "createdAt": "2026-03-25T17:00:28.934Z",
                "transaction_type": "withdrawal",
                "transaction_description": "withdrawal processed at Schmidt LLC for ZWL 73.03, using card ending ****2163. Account: ***6800.",
                "transactin_amount": "315.77",
                "id": "54fabdbdb35bd6ef5eb4dd7e"
            },
            {
                "createdAt": "2026-03-26T07:45:11.641Z",
                "transaction_type": "withdrawal",
                "transaction_description": "You made a payment of NAD 17.19 at Stamm - Walsh using card ending in ****8224 from account ***4671.",
                "transactin_amount": "855.54",
                "id": "e1558fdfcc4fd84defa1f0b4"
            }
        ],
        "person_id": "ccbb0e92c23d52efbc14fce1"
    },
    {
        "account_number": "16994365",
        "iban": "MR9378004327280260284900185",
        "currency_code": "JPY",
        "balance": "132.08",
        "id": "eadd0aae2ee1ffd48da5c6ef",
        "transactions": [
            {
                "createdAt": "2026-03-25T18:00:49.966Z",
                "transaction_type": "invoice",
                "transaction_description": "deposit at Kling, Balistreri and Haley with a card ending in ****7448 for IRR 385.67 from account ***1592.",
                "transactin_amount": "723.91",
                "id": "d2d3cc2feeed5a8dae9cee0f"
            },
            {
                "createdAt": "2026-03-26T06:09:33.274Z",
                "transaction_type": "deposit",
                "transaction_description": "Payment of ETB 823.45 for payment at Cormier, Pagac and Metz, processed with card ending ****6921 linked to account ***8729.",
                "transactin_amount": "550.78",
                "id": "cb9c5b32a1ab1bf41af5cdb3"
            }
        ],
        "person_id": "386c35ff1ab6faee3b6c39f5"
    },
    {
        "account_number": "13542022",
        "iban": "LV05QIBC4108M77814051",
        "currency_code": "PKR",
        "balance": "527.73",
        "id": "aadac45874f30199c4c9bde5",
        "transactions": [
            {
                "createdAt": "2026-03-26T06:24:43.192Z",
                "transaction_type": "deposit",
                "transaction_description": "A deposit for QAR 225.76 was made at Reichert, Emard and Trantow via card ending ****8371 on account ***1043.",
                "transactin_amount": "343.29",
                "id": "e1a9a9b2fd32afebc846fb0e"
            },
            {
                "createdAt": "2026-03-25T22:37:43.448Z",
                "transaction_type": "payment",
                "transaction_description": "deposit transaction at Morar - Tillman using card ending with ****2282 for HUF 545.68 in account ***2679.",
                "transactin_amount": "125.00",
                "id": "c65fba992c0dba8aac4bcd1d"
            }
        ],
        "person_id": "cdb681c0f62daecdfdd8be1e"
    },
    {
        "account_number": "00676860",
        "iban": "IE31T90700100360006536",
        "currency_code": "ANG",
        "balance": "823.44",
        "id": "3f3f188669dd6b704cfdcc8e",
        "transactions": [
            {
                "createdAt": "2026-03-26T03:23:18.061Z",
                "transaction_type": "invoice",
                "transaction_description": "withdrawal at Wintheiser Group with a card ending in ****1315 for ETB 818.00 from account ***8165.",
                "transactin_amount": "766.43",
                "id": "b995b4deafcc6bef8d98ebbb"
            },
            {
                "createdAt": "2026-03-25T15:55:52.409Z",
                "transaction_type": "deposit",
                "transaction_description": "withdrawal transaction at Schowalter LLC using card ending with ****5948 for QAR 957.29 in account ***1298.",
                "transactin_amount": "351.49",
                "id": "34e87d1e3fcfb45daebc6fac"
            }
        ],
        "person_id": "e4efba5446a010b595b6c5ee"
    },
    {
        "account_number": "65372576",
        "iban": "SA8797850K752E68A7061731",
        "currency_code": "GMD",
        "balance": "639.58",
        "id": "a12ccae5a7c5c25dda5a9ab0",
        "transactions": [
            {
                "createdAt": "2026-03-26T06:08:44.367Z",
                "transaction_type": "payment",
                "transaction_description": "You made a deposit of QAR 987.67 at Kutch, Larson and Harvey using card ending in ****4329 from account ***6545.",
                "transactin_amount": "55.96",
                "id": "aeb4fcaf340463f836fe4f36"
            },
            {
                "createdAt": "2026-03-25T17:06:59.342Z",
                "transaction_type": "withdrawal",
                "transaction_description": "withdrawal of COP 932.33 at Conn and Sons charged to account ending in 7160 using card ending in ****8368.",
                "transactin_amount": "457.54",
                "id": "d4bfc6a9da67dbbbdefa7c97"
            }
        ],
        "person_id": "31a32a5e0db01319ad2d75e1"
    },
    {
        "account_number": "82095396",
        "iban": "NO7654579534006",
        "currency_code": "IQD",
        "balance": "374.34",
        "id": "ceba7104eb75da300cab6b20",
        "transactions": [
            {
                "createdAt": "2026-03-26T07:01:03.894Z",
                "transaction_type": "invoice",
                "transaction_description": "payment processed at Mosciski - McClure for JPY 356.30, using card ending ****2239. Account: ***5330.",
                "transactin_amount": "347.21",
                "id": "b9acdbdd5e3f0ddd7ed64f2b"
            },
            {
                "createdAt": "2026-03-25T23:27:15.743Z",
                "transaction_type": "deposit",
                "transaction_description": "Payment of GIP 804.24 for withdrawal at Quigley - Schneider, processed with card ending ****7014 linked to account ***3168.",
                "transactin_amount": "588.57",
                "id": "aba87cee4fbc46ab6e82d3ed"
            }
        ],
        "person_id": "75ea4616c36ad4f95e3decca"
    },
    {
        "account_number": "08258136",
        "iban": "HR2436340981308207072",
        "currency_code": "PHP",
        "balance": "730.59",
        "id": "dafa42b07a1b8b0f8806acdd",
        "transactions": [
            {
                "createdAt": "2026-03-25T12:51:29.410Z",
                "transaction_type": "withdrawal",
                "transaction_description": "Your invoice of CDF 474.93 at Herzog and Sons was successful. Charged via card ****6256 to account ***7489.",
                "transactin_amount": "876.48",
                "id": "da122739bc82fea573d044aa"
            },
            {
                "createdAt": "2026-03-25T22:19:58.369Z",
                "transaction_type": "deposit",
                "transaction_description": "payment confirmed at Grimes, Hyatt and Schultz for TJS 405.13, card ending in ****0102 associated with account ***5113.",
                "transactin_amount": "515.84",
                "id": "ca0ceeb709cb5225ec2b6fda"
            }
        ],
        "person_id": "aa505ec2735fb51aa17d27f4"
    },
    {
        "account_number": "13210261",
        "iban": "BG10SAQR28699374R74918",
        "currency_code": "LYD",
        "balance": "691.53",
        "id": "ada6cf2b5f7d8bf3ae1f14ba",
        "transactions": [
            {
                "createdAt": "2026-03-25T15:43:38.076Z",
                "transaction_type": "invoice",
                "transaction_description": "Your withdrawal of TWD 931.77 at Koelpin - Davis was successful. Charged via card ****2696 to account ***1338.",
                "transactin_amount": "771.09",
                "id": "d2a48e3de09eb87ef0a57e04"
            },
            {
                "createdAt": "2026-03-26T03:12:05.115Z",
                "transaction_type": "payment",
                "transaction_description": "You made a withdrawal of SRD 372.35 at Pfeffer Inc using card ending in ****1546 from account ***6671.",
                "transactin_amount": "457.54",
                "id": "cbededf8eeb36bbb4a5a01b7"
            }
        ],
        "person_id": "e4daaf4a9eb2f1422eda1aba"
    },
    {
        "account_number": "86829447",
        "iban": "TR548404530258703665507546",
        "currency_code": "BYN",
        "balance": "639.02",
        "id": "c39db757cc0ecf3114c365fc",
        "transactions": [
            {
                "createdAt": "2026-03-25T18:10:18.649Z",
                "transaction_type": "invoice",
                "transaction_description": "deposit of ERN 806.49 at Huel LLC charged to account ending in 6918 using card ending in ****1822.",
                "transactin_amount": "42.65",
                "id": "caba6bc981e2da49a25a0dde"
            },
            {
                "createdAt": "2026-03-26T08:55:10.899Z",
                "transaction_type": "deposit",
                "transaction_description": "payment of UYU 149.99 at Balistreri LLC charged to account ending in 7882 using card ending in ****3686.",
                "transactin_amount": "210.86",
                "id": "f30dce7de6c89cdd22ca7fba"
            }
        ],
        "person_id": "c6f7fc915ccfb0f723bfd45e"
    },
    {
        "account_number": "17925763",
        "iban": "VG91WPCA8060009760500502",
        "currency_code": "SGD",
        "balance": "249.36",
        "id": "d0c7bca0dbde0ebe3ee3d098",
        "transactions": [
            {
                "createdAt": "2026-03-26T03:29:05.655Z",
                "transaction_type": "payment",
                "transaction_description": "deposit processed at Green - Feil for CRC 782.04, using card ending ****0466. Account: ***8209.",
                "transactin_amount": "100.51",
                "id": "e26ddbdf0e4cda9fbfc1f5de"
            },
            {
                "createdAt": "2026-03-25T20:20:23.498Z",
                "transaction_type": "withdrawal",
                "transaction_description": "A deposit of RON 607.39 occurred at Cremin - Champlin using a card ending in ****6540 for account ***1832.",
                "transactin_amount": "723.35",
                "id": "ae4cda93efadae85ace1ef34"
            }
        ],
        "person_id": "cdb681c0f62daecdfdd8be1e"
    },
    {
        "account_number": "36633621",
        "iban": "EE641004500351802059",
        "currency_code": "PKR",
        "balance": "31.81",
        "id": "dfece2780d97e22efe95cfc7",
        "transactions": [
            {
                "createdAt": "2026-03-26T00:34:44.257Z",
                "transaction_type": "invoice",
                "transaction_description": "A invoice of STN 806.14 occurred at Spencer and Sons using a card ending in ****5867 for account ***1183.",
                "transactin_amount": "928.29",
                "id": "ce34fcca7f7c26bf84dcf6fe"
            }
        ],
        "person_id": "e4efba5446a010b595b6c5ee"
    },
    {
        "account_number": "32544408",
        "iban": "BH24UXRIL668D99D450X30",
        "currency_code": "MDL",
        "balance": "851.85",
        "id": "3d57dc0df13f0f8bcdec62ff",
        "transactions": [
            {
                "createdAt": "2026-03-25T18:11:35.020Z",
                "transaction_type": "payment",
                "transaction_description": "deposit confirmed at Koelpin, Murphy and Dibbert for GEL 661.28, card ending in ****5903 associated with account ***6113.",
                "transactin_amount": "29.31",
                "id": "5db70ad7dfabe01a8b9f07e2"
            }
        ],
        "person_id": "31a32a5e0db01319ad2d75e1"
    },
    {
        "account_number": "23035122",
        "iban": "PK33MPCV2002002994981982",
        "currency_code": "KMF",
        "balance": "854.21",
        "id": "2e1cb62ea0d4c9cd7ed299fe",
        "transactions": [
            {
                "createdAt": "2026-03-25T23:02:39.460Z",
                "transaction_type": "deposit",
                "transaction_description": "You made a payment of KZT 681.24 at Kozey - Wolff using card ending in ****3762 from account ***4917.",
                "transactin_amount": "370.48",
                "id": "3df77fbd061d722bdeabcd72"
            }
        ],
        "person_id": "75ea4616c36ad4f95e3decca"
    },
    {
        "account_number": "35451440",
        "iban": "LV94WXRZ223454YV1Q812",
        "currency_code": "COP",
        "balance": "724.76",
        "id": "69997cb5baafd43ca315d6a2",
        "transactions": [
            {
                "createdAt": "2026-03-25T17:48:40.517Z",
                "transaction_type": "payment",
                "transaction_description": "withdrawal of INR 735.30 at Hackett - Kessler charged to account ending in 7161 using card ending in ****7823.",
                "transactin_amount": "806.61",
                "id": "c882d20b68efeecb7342ae8c"
            }
        ],
        "person_id": "aa505ec2735fb51aa17d27f4"
    },
    {
        "account_number": "15091098",
        "iban": "IL740108998001991627005",
        "currency_code": "ETB",
        "balance": "890.94",
        "id": "6177e9ce640fb56bd7c1733c",
        "transactions": [
            {
                "createdAt": "2026-03-26T01:42:15.278Z",
                "transaction_type": "withdrawal",
                "transaction_description": "Transaction alert: payment at Emard LLC using card ending ****7194 for an amount of CDF 2.24 on account ***0751.",
                "transactin_amount": "629.97",
                "id": "38e2baa7a49aa8eb44e0740a"
            }
        ],
        "person_id": "e4daaf4a9eb2f1422eda1aba"
    },
    {
        "account_number": "32269828",
        "iban": "CZ2100540025370747358002",
        "currency_code": "AZN",
        "balance": "360.50",
        "id": "2fbaa1ca3a7445532bc73cac",
        "transactions": [
            {
                "createdAt": "2026-03-26T09:16:39.116Z",
                "transaction_type": "withdrawal",
                "transaction_description": "payment of LBP 777.93 at Stiedemann, Bergnaum and Gislason charged to account ending in 0969 using card ending in ****1222.",
                "transactin_amount": "958.35",
                "id": "0bafae129ca84040936bb24d"
            }
        ],
        "person_id": "c6f7fc915ccfb0f723bfd45e"
    },
    {
        "account_number": "72181783",
        "iban": "AZ10WCYC50010895047670703931",
        "currency_code": "AUD",
        "balance": "85.95",
        "id": "37d4aec87f8e1dde7f55fbc5",
        "transactions": [
            {
                "createdAt": "2026-03-25T16:45:25.222Z",
                "transaction_type": "withdrawal",
                "transaction_description": "withdrawal at Corwin Inc with a card ending in ****3986 for ISK 893.80 from account ***6467.",
                "transactin_amount": "948.79",
                "id": "eafd5ceb9a4b9d1b5e78b89a"
            }
        ],
        "person_id": "a67e8ea4ef4525b8c9c14f1e"
    },
    {
        "account_number": "71018269",
        "iban": "MR3500522109240090042300453",
        "currency_code": "SHP",
        "balance": "16.51",
        "id": "1ea59e0de2bbaff6b4987fcd",
        "transactions": [
            {
                "createdAt": "2026-03-26T05:07:40.367Z",
                "transaction_type": "payment",
                "transaction_description": "Your payment of THB 766.10 at Becker LLC was successful. Charged via card ****2369 to account ***7489.",
                "transactin_amount": "579.19",
                "id": "1ceaa49cb291ceebe965b4e2"
            }
        ],
        "person_id": "ac217bea6cbf219d25f3b9b4"
    },
    {
        "account_number": "39065315",
        "iban": "AZ61ZBON69004600600466027066",
        "currency_code": "UAH",
        "balance": "850.71",
        "id": "328adbf5ef1a3afbabfd31c6",
        "transactions": [
            {
                "createdAt": "2026-03-26T11:09:55.011Z",
                "transaction_type": "invoice",
                "transaction_description": "You made a withdrawal of MKD 597.51 at Windler - Ryan using card ending in ****6992 from account ***1501.",
                "transactin_amount": "27.99",
                "id": "cea4bfdfafe7efd68db3dbef"
            }
        ],
        "person_id": "f9817de6124ae4fa4d8b766a"
    },
    {
        "account_number": "81976219",
        "iban": "GE93TZ8300220048051663",
        "currency_code": "BWP",
        "balance": "34.30",
        "id": "fb4ada7eb47641dbdc987b45",
        "transactions": [
            {
                "createdAt": "2026-03-26T05:23:38.890Z",
                "transaction_type": "withdrawal",
                "transaction_description": "deposit transaction at Leffler Group using card ending with ****3995 for RSD 644.27 in account ***4588.",
                "transactin_amount": "370.46",
                "id": "eecc471d4d9c0b3b0b9af3ab"
            }
        ],
        "person_id": "f01cb12bae4ccdd5a8ea7a8c"
    },
    {
        "account_number": "83543552",
        "iban": "TN8634196009501195205382",
        "currency_code": "INR",
        "balance": "988.67",
        "id": "2be83409ba77179dfea4febb",
        "transactions": [
            {
                "createdAt": "2026-03-26T01:44:14.496Z",
                "transaction_type": "withdrawal",
                "transaction_description": "Payment of KHR 232.46 for withdrawal at Leffler Inc, processed with card ending ****9615 linked to account ***3420.",
                "transactin_amount": "426.57",
                "id": "fee1a62cc9cc4e62552f2612"
            }
        ],
        "person_id": "bf49a6e64ead9430d8041aca"
    },
    {
        "account_number": "64450666",
        "iban": "FR16702302405881H1233X8L685",
        "currency_code": "MNT",
        "balance": "954.05",
        "id": "afd2ab14cdff9d9a76fed523",
        "transactions": [
            {
                "createdAt": "2026-03-25T18:45:18.109Z",
                "transaction_type": "withdrawal",
                "transaction_description": "You made a deposit of PEN 714.55 at Kassulke LLC using card ending in ****8251 from account ***8935.",
                "transactin_amount": "584.73",
                "id": "b0436dcafdac877f15e9bb8f"
            }
        ],
        "person_id": "cdb681c0f62daecdfdd8be1e"
    },
    {
        "account_number": "95378218",
        "iban": "BA332652968336968282",
        "currency_code": "TMT",
        "balance": "672.28",
        "id": "5ffd8d292dd11bd0aaeec894",
        "transactions": [
            {
                "createdAt": "2026-03-26T09:39:48.458Z",
                "transaction_type": "withdrawal",
                "transaction_description": "Payment of SYP 583.61 for deposit at Murphy - McDermott, processed with card ending ****7323 linked to account ***6266.",
                "transactin_amount": "268.95",
                "id": "c094e6ab9dbc79b0bea1fd0c"
            }
        ],
        "person_id": "e4efba5446a010b595b6c5ee"
    },
    {
        "account_number": "91251136",
        "iban": "MK87016D16032505904",
        "currency_code": "SSP",
        "balance": "848.15",
        "id": "b96f28bebadfb76db8cac443",
        "transactions": [
            {
                "createdAt": "2026-03-26T03:34:16.487Z",
                "transaction_type": "withdrawal",
                "transaction_description": "Payment of BBD 967.96 for invoice at Harris, Lebsack and Bednar, processed with card ending ****8136 linked to account ***2013.",
                "transactin_amount": "406.91",
                "id": "2f910bfb72d6ca19abacbe1a"
            }
        ],
        "person_id": "31a32a5e0db01319ad2d75e1"
    },
    {
        "account_number": "22336016",
        "iban": "BG95ACXM40426274G3623K",
        "currency_code": "AUD",
        "balance": "6.01",
        "id": "2dda49ced4aedbbda13255bb",
        "transactions": [
            {
                "createdAt": "2026-03-25T17:11:33.118Z",
                "transaction_type": "invoice",
                "transaction_description": "A payment for AED 473.46 was made at Boyle, Kemmer and Nikolaus via card ending ****6207 on account ***7214.",
                "transactin_amount": "284.90",
                "id": "88ce91de5faacaebd59aaedd"
            }
        ],
        "person_id": "75ea4616c36ad4f95e3decca"
    }
]